pysource.sh
setup.py
pysource/__init__.py
pysource/arguments.py
pysource/client.py
pysource/config.py
pysource/daemonizer.py
pysource/global_env.py
pysource/handlers.py
pysource/main.py
pysource/registry.py
pysource/shell.py
pysource/transport.py
pysource.egg-info/PKG-INFO
pysource.egg-info/SOURCES.txt
pysource.egg-info/dependency_links.txt
pysource.egg-info/not-zip-safe
pysource.egg-info/requires.txt
pysource.egg-info/top_level.txt