Metadata-Version: 1.1
Name: pysource
Version: 0.1.1
Summary: "source" and run python functions in bash
Home-page: https://github.com/dankilman/pysource
Author: Dan Kilman
Author-email: dankilman@gmail.com
License: Apache License, Version 2.0
Keywords: bash shell source function
Platform: UNKNOWN
Classifier: Development Status :: 3 - Alpha
Classifier: Environment :: Console
Classifier: Intended Audience :: Developers
Classifier: Intended Audience :: System Administrators
Classifier: License :: OSI Approved :: Apache Software License
Classifier: Operating System :: POSIX :: Linux
Classifier: Programming Language :: Python :: 2 :: Only
Classifier: Programming Language :: Python :: 2.7
Classifier: Programming Language :: Unix Shell
Classifier: Topic :: Software Development
Classifier: Topic :: System :: Shells
Classifier: Topic :: System :: System Shells
Classifier: Topic :: Utilities
